binaryornot/__init__.py
binaryornot/check.py
binaryornot/helpers.py
binaryornot-0.4.3.dist-info/DESCRIPTION.rst
binaryornot-0.4.3.dist-info/METADATA
binaryornot-0.4.3.dist-info/RECORD
binaryornot-0.4.3.dist-info/WHEEL
binaryornot-0.4.3.dist-info/metadata.json
binaryornot-0.4.3.dist-info/top_level.txt
