Metadata-Version: 1.1
Name: binaryornot
Version: 0.4.3
Summary: Ultra-lightweight pure Python package to check if a file is binary or text.
Home-page: https://github.com/audreyr/binaryornot
Author: Audrey Roy Greenfeld
Author-email: aroy@alum.mit.edu
License: BSD
Keywords: binaryornot
Platform: UNKNOWN
Classifier: Development Status :: 5 - Production/Stable
Classifier: Intended Audience :: Developers
Classifier: License :: OSI Approved :: BSD License
Classifier: Natural Language :: English
Classifier: Programming Language :: Python :: 2
Classifier: Programming Language :: Python :: 2.7
Classifier: Programming Language :: Python :: 3
Classifier: Programming Language :: Python :: 3.3
Classifier: Programming Language :: Python :: 3.4
Classifier: Programming Language :: Python :: 3.5
Classifier: Programming Language :: Python :: 3.6
